[
    {
        "id": null,
        "exchangeName": null,
        "symbol": null,
        "baseCoin": null,
        "begin": 1733760000000,
        "interval": "15m",
        "netLongsOpen": null,
        "netLongsHigh": 582165,
        "netLongsClose": 419804,
        "netLongsLow": -489813,
        "netShortsOpen": null,
        "netShortsClose": 917947,
        "netShortsHigh": 1307185,
        "netShortsLow": -175564
    },
    {
        "id": null,
        "exchangeName": null,
        "symbol": null,
        "baseCoin": null,
        "begin": 1733760900000,
        "interval": "15m",
        "netLongsOpen": null,
        "netLongsHigh": 538394,
        "netLongsClose": 538394,
        "netLongsLow": -118398,
        "netShortsOpen": null,
        "netShortsClose": -177114,
        "netShortsHigh": 0,
        "netShortsLow": -223283
    },
    {
        "id": null,
        "exchangeName": null,
        "symbol": null,
        "baseCoin": null,
        "begin": 1733761800000,
        "interval": "15m",
        "netLongsOpen": null,
        "netLongsHigh": 321216,
        "netLongsClose": 321216,
        "netLongsLow": -457255,
        "netShortsOpen": null,
        "netShortsClose": 179493,
        "netShortsHigh": 497968,
        "netShortsLow": 0
    },
    {
        "id": null,
        "exchangeName": null,
        "symbol": null,
        "baseCoin": null,
        "begin": 1733762700000,
        "interval": "15m",
        "netLongsOpen": null,
        "netLongsHigh": 473651,
        "netLongsClose": -571949,
        "netLongsLow": -571949,
        "netShortsOpen": null,
        "netShortsClose": 113453,
        "netShortsHigh": 156600,
        "netShortsLow": -358552
    },
    {
        "id": null,
        "exchangeName": null,
        "symbol": null,
        "baseCoin": null,
        "begin": 1733763600000,
        "interval": "15m",
        "netLongsOpen": null,
        "netLongsHigh": 608972,
        "netLongsClose": 608972,
        "netLongsLow": 0,
        "netShortsOpen": null,
        "netShortsClose": -188289,
        "netShortsHigh": 75456,
        "netShortsLow": -188289
    },
    {
        "id": null,
        "exchangeName": null,
        "symbol": null,
        "baseCoin": null,
        "begin": 1733764500000,
        "interval": "15m",
        "netLongsOpen": null,
        "netLongsHigh": 1146990,
        "netLongsClose": 1078479,
        "netLongsLow": 0,
        "netShortsOpen": null,
        "netShortsClose": -327335,
        "netShortsHigh": 194645,
        "netShortsLow": -327335
    },
    {
        "id": null,
        "exchangeName": null,
        "symbol": null,
        "baseCoin": null,
        "begin": 1733765400000,
        "interval": "15m",
        "netLongsOpen": null,
        "netLongsHigh": 327936,
        "netLongsClose": 327936,
        "netLongsLow": 0,
        "netShortsOpen": null,
        "netShortsClose": -482906,
        "netShortsHigh": 47515,
        "netShortsLow": -482906
    },
    {
        "id": null,
        "exchangeName": null,
        "symbol": null,
        "baseCoin": null,
        "begin": 1733766300000,
        "interval": "15m",
        "netLongsOpen": null,
        "netLongsHigh": 331373,
        "netLongsClose": 226516,
        "netLongsLow": 0,
        "netShortsOpen": null,
        "netShortsClose": -363579,
        "netShortsHigh": 38172,
        "netShortsLow": -363579
    },
    {
        "id": null,
        "exchangeName": null,
        "symbol": null,
        "baseCoin": null,
        "begin": 1733767200000,
        "interval": "15m",
        "netLongsOpen": null,
        "netLongsHigh": 131755,
        "netLongsClose": -747464,
        "netLongsLow": -872432,
        "netShortsOpen": null,
        "netShortsClose": -191922,
        "netShortsHigh": 0,
        "netShortsLow": -423887
    },
    {
        "id": null,
        "exchangeName": null,
        "symbol": null,
        "baseCoin": null,
        "begin": 1733768100000,
        "interval": "15m",
        "netLongsOpen": null,
        "netLongsHigh": 819717,
        "netLongsClose": 819717,
        "netLongsLow": -76790,
        "netShortsOpen": null,
        "netShortsClose": -521706,
        "netShortsHigh": 23178,
        "netShortsLow": -521706
    },
    {
        "id": null,
        "exchangeName": null,
        "symbol": null,
        "baseCoin": null,
        "begin": 1733769000000,
        "interval": "15m",
        "netLongsOpen": null,
        "netLongsHigh": 204324,
        "netLongsClose": -573443,
        "netLongsLow": -981487,
        "netShortsOpen": null,
        "netShortsClose": 317650,
        "netShortsHigh": 477110,
        "netShortsLow": 0
    },
    {
        "id": null,
        "exchangeName": null,
        "symbol": null,
        "baseCoin": null,
        "begin": 1733769900000,
        "interval": "15m",
        "netLongsOpen": null,
        "netLongsHigh": 238966,
        "netLongsClose": 146140,
        "netLongsLow": 0,
        "netShortsOpen": null,
        "netShortsClose": 84015,
        "netShortsHigh": 84015,
        "netShortsLow": -33019
    },
    {
        "id": null,
        "exchangeName": null,
        "symbol": null,
        "baseCoin": null,
        "begin": 1733770800000,
        "interval": "15m",
        "netLongsOpen": null,
        "netLongsHigh": 0,
        "netLongsClose": -1153818,
        "netLongsLow": -1372127,
        "netShortsOpen": null,
        "netShortsClose": 3096618,
        "netShortsHigh": 3276793,
        "netShortsLow": -217274
    },
    {
        "id": null,
        "exchangeName": null,
        "symbol": null,
        "baseCoin": null,
        "begin": 1733771700000,
        "interval": "15m",
        "netLongsOpen": null,
        "netLongsHigh": 625204,
        "netLongsClose": 562685,
        "netLongsLow": 0,
        "netShortsOpen": null,
        "netShortsClose": -236582,
        "netShortsHigh": 0,
        "netShortsLow": -290171
    },
    {
        "id": null,
        "exchangeName": null,
        "symbol": null,
        "baseCoin": null,
        "begin": 1733772600000,
        "interval": "15m",
        "netLongsOpen": null,
        "netLongsHigh": 443775,
        "netLongsClose": 443775,
        "netLongsLow": 0,
        "netShortsOpen": null,
        "netShortsClose": -113217,
        "netShortsHigh": 85987,
        "netShortsLow": -113217
    },
    {
        "id": null,
        "exchangeName": null,
        "symbol": null,
        "baseCoin": null,
        "begin": 1733773500000,
        "interval": "15m",
        "netLongsOpen": null,
        "netLongsHigh": 140501,
        "netLongsClose": 140501,
        "netLongsLow": -165750,
        "netShortsOpen": null,
        "netShortsClose": -788425,
        "netShortsHigh": 103455,
        "netShortsLow": -788425
    },
    {
        "id": null,
        "exchangeName": null,
        "symbol": null,
        "baseCoin": null,
        "begin": 1733774400000,
        "interval": "15m",
        "netLongsOpen": null,
        "netLongsHigh": 52938,
        "netLongsClose": -4795632,
        "netLongsLow": -4795632,
        "netShortsOpen": null,
        "netShortsClose": 3191066,
        "netShortsHigh": 3191066,
        "netShortsLow": -162383
    },
    {
        "id": null,
        "exchangeName": null,
        "symbol": null,
        "baseCoin": null,
        "begin": 1733775300000,
        "interval": "15m",
        "netLongsOpen": null,
        "netLongsHigh": 131946,
        "netLongsClose": -13163125,
        "netLongsLow": -13163125,
        "netShortsOpen": null,
        "netShortsClose": 1511495,
        "netShortsHigh": 2153560,
        "netShortsLow": 0
    },
    {
        "id": null,
        "exchangeName": null,
        "symbol": null,
        "baseCoin": null,
        "begin": 1733776200000,
        "interval": "15m",
        "netLongsOpen": null,
        "netLongsHigh": 739555,
        "netLongsClose": -14631293,
        "netLongsLow": -14631293,
        "netShortsOpen": null,
        "netShortsClose": 8805674,
        "netShortsHigh": 8805674,
        "netShortsLow": -483996
    },
    {
        "id": null,
        "exchangeName": null,
        "symbol": null,
        "baseCoin": null,
        "begin": 1733777100000,
        "interval": "15m",
        "netLongsOpen": null,
        "netLongsHigh": 253673,
        "netLongsClose": 253673,
        "netLongsLow": -6183392,
        "netShortsOpen": null,
        "netShortsClose": 2182036,
        "netShortsHigh": 2708090,
        "netShortsLow": -189077
    },
    {
        "id": null,
        "exchangeName": null,
        "symbol": null,
        "baseCoin": null,
        "begin": 1733778000000,
        "interval": "15m",
        "netLongsOpen": null,
        "netLongsHigh": 0,
        "netLongsClose": -9199105,
        "netLongsLow": -15913442,
        "netShortsOpen": null,
        "netShortsClose": 25979706,
        "netShortsHigh": 35103990,
        "netShortsLow": 0
    },
    {
        "id": null,
        "exchangeName": null,
        "symbol": null,
        "baseCoin": null,
        "begin": 1733778900000,
        "interval": "15m",
        "netLongsOpen": null,
        "netLongsHigh": 0,
        "netLongsClose": -13173319,
        "netLongsLow": -13173319,
        "netShortsOpen": null,
        "netShortsClose": 85399,
        "netShortsHigh": 85399,
        "netShortsLow": -2787211
    },
    {
        "id": null,
        "exchangeName": null,
        "symbol": null,
        "baseCoin": null,
        "begin": 1733779800000,
        "interval": "15m",
        "netLongsOpen": null,
        "netLongsHigh": 30327,
        "netLongsClose": -5937203,
        "netLongsLow": -5937203,
        "netShortsOpen": null,
        "netShortsClose": -336334,
        "netShortsHigh": 0,
        "netShortsLow": -1160298
    },
    {
        "id": null,
        "exchangeName": null,
        "symbol": null,
        "baseCoin": null,
        "begin": 1733780700000,
        "interval": "15m",
        "netLongsOpen": null,
        "netLongsHigh": 0,
        "netLongsClose": -11738963,
        "netLongsLow": -11738963,
        "netShortsOpen": null,
        "netShortsClose": -1242908,
        "netShortsHigh": 0,
        "netShortsLow": -2602381
    },
    {
        "id": null,
        "exchangeName": null,
        "symbol": null,
        "baseCoin": null,
        "begin": 1733781600000,
        "interval": "15m",
        "netLongsOpen": null,
        "netLongsHigh": 0,
        "netLongsClose": -7206768,
        "netLongsLow": -7206768,
        "netShortsOpen": null,
        "netShortsClose": 1277365,
        "netShortsHigh": 1738881,
        "netShortsLow": 0
    },
    {
        "id": null,
        "exchangeName": null,
        "symbol": null,
        "baseCoin": null,
        "begin": 1733782500000,
        "interval": "15m",
        "netLongsOpen": null,
        "netLongsHigh": 829576,
        "netLongsClose": 829576,
        "netLongsLow": -557476,
        "netShortsOpen": null,
        "netShortsClose": -1989825,
        "netShortsHigh": 390695,
        "netShortsLow": -2088821
    },
    {
        "id": null,
        "exchangeName": null,
        "symbol": null,
        "baseCoin": null,
        "begin": 1733783400000,
        "interval": "15m",
        "netLongsOpen": null,
        "netLongsHigh": 0,
        "netLongsClose": -359926,
        "netLongsLow": -1064340,
        "netShortsOpen": null,
        "netShortsClose": -387447,
        "netShortsHigh": 675549,
        "netShortsLow": -387447
    },
    {
        "id": null,
        "exchangeName": null,
        "symbol": null,
        "baseCoin": null,
        "begin": 1733784300000,
        "interval": "15m",
        "netLongsOpen": null,
        "netLongsHigh": 727282,
        "netLongsClose": 412396,
        "netLongsLow": 0,
        "netShortsOpen": null,
        "netShortsClose": -242781,
        "netShortsHigh": 96444,
        "netShortsLow": -468114
    },
    {
        "id": null,
        "exchangeName": null,
        "symbol": null,
        "baseCoin": null,
        "begin": 1733785200000,
        "interval": "15m",
        "netLongsOpen": null,
        "netLongsHigh": 216030,
        "netLongsClose": -2006589,
        "netLongsLow": -2708310,
        "netShortsOpen": null,
        "netShortsClose": -1153240,
        "netShortsHigh": 683086,
        "netShortsLow": -1153240
    },
    {
        "id": null,
        "exchangeName": null,
        "symbol": null,
        "baseCoin": null,
        "begin": 1733786100000,
        "interval": "15m",
        "netLongsOpen": null,
        "netLongsHigh": 0,
        "netLongsClose": -2980855,
        "netLongsLow": -3097529,
        "netShortsOpen": null,
        "netShortsClose": -3699656,
        "netShortsHigh": 0,
        "netShortsLow": -3723983
    },
    {
        "id": null,
        "exchangeName": null,
        "symbol": null,
        "baseCoin": null,
        "begin": 1733787000000,
        "interval": "15m",
        "netLongsOpen": null,
        "netLongsHigh": 0,
        "netLongsClose": -3694572,
        "netLongsLow": -3694572,
        "netShortsOpen": null,
        "netShortsClose": -1309902,
        "netShortsHigh": 194322,
        "netShortsLow": -1398200
    },
    {
        "id": null,
        "exchangeName": null,
        "symbol": null,
        "baseCoin": null,
        "begin": 1733787900000,
        "interval": "15m",
        "netLongsOpen": null,
        "netLongsHigh": 364337,
        "netLongsClose": -1344060,
        "netLongsLow": -1344060,
        "netShortsOpen": null,
        "netShortsClose": -2290446,
        "netShortsHigh": 522443,
        "netShortsLow": -2290446
    },
    {
        "id": null,
        "exchangeName": null,
        "symbol": null,
        "baseCoin": null,
        "begin": 1733788800000,
        "interval": "15m",
        "netLongsOpen": null,
        "netLongsHigh": 0,
        "netLongsClose": -2972339,
        "netLongsLow": -2972339,
        "netShortsOpen": null,
        "netShortsClose": 735539,
        "netShortsHigh": 735539,
        "netShortsLow": -383197
    },
    {
        "id": null,
        "exchangeName": null,
        "symbol": null,
        "baseCoin": null,
        "begin": 1733789700000,
        "interval": "15m",
        "netLongsOpen": null,
        "netLongsHigh": 707162,
        "netLongsClose": -976717,
        "netLongsLow": -976717,
        "netShortsOpen": null,
        "netShortsClose": 1295604,
        "netShortsHigh": 1295604,
        "netShortsLow": -150216
    },
    {
        "id": null,
        "exchangeName": null,
        "symbol": null,
        "baseCoin": null,
        "begin": 1733790600000,
        "interval": "15m",
        "netLongsOpen": null,
        "netLongsHigh": 1492040,
        "netLongsClose": 1425015,
        "netLongsLow": -474486,
        "netShortsOpen": null,
        "netShortsClose": -7960642,
        "netShortsHigh": 0,
        "netShortsLow": -7960642
    },
    {
        "id": null,
        "exchangeName": null,
        "symbol": null,
        "baseCoin": null,
        "begin": 1733791500000,
        "interval": "15m",
        "netLongsOpen": null,
        "netLongsHigh": 1575324,
        "netLongsClose": 1328705,
        "netLongsLow": -276909,
        "netShortsOpen": null,
        "netShortsClose": -1500800,
        "netShortsHigh": 149528,
        "netShortsLow": -1500800
    },
    {
        "id": null,
        "exchangeName": null,
        "symbol": null,
        "baseCoin": null,
        "begin": 1733792400000,
        "interval": "15m",
        "netLongsOpen": null,
        "netLongsHigh": 0,
        "netLongsClose": -1408325,
        "netLongsLow": -1408325,
        "netShortsOpen": null,
        "netShortsClose": 1238475,
        "netShortsHigh": 1238475,
        "netShortsLow": -367046
    },
    {
        "id": null,
        "exchangeName": null,
        "symbol": null,
        "baseCoin": null,
        "begin": 1733793300000,
        "interval": "15m",
        "netLongsOpen": null,
        "netLongsHigh": 280008,
        "netLongsClose": -2373642,
        "netLongsLow": -2373642,
        "netShortsOpen": null,
        "netShortsClose": 1271661,
        "netShortsHigh": 1271661,
        "netShortsLow": 0
    },
    {
        "id": null,
        "exchangeName": null,
        "symbol": null,
        "baseCoin": null,
        "begin": 1733794200000,
        "interval": "15m",
        "netLongsOpen": null,
        "netLongsHigh": 9551,
        "netLongsClose": -1448166,
        "netLongsLow": -2180521,
        "netShortsOpen": null,
        "netShortsClose": 609698,
        "netShortsHigh": 907770,
        "netShortsLow": -266350
    },
    {
        "id": null,
        "exchangeName": null,
        "symbol": null,
        "baseCoin": null,
        "begin": 1733795100000,
        "interval": "15m",
        "netLongsOpen": null,
        "netLongsHigh": 0,
        "netLongsClose": -2245549,
        "netLongsLow": -2245549,
        "netShortsOpen": null,
        "netShortsClose": -118916,
        "netShortsHigh": 261317,
        "netShortsLow": -193789
    },
    {
        "id": null,
        "exchangeName": null,
        "symbol": null,
        "baseCoin": null,
        "begin": 1733796000000,
        "interval": "15m",
        "netLongsOpen": null,
        "netLongsHigh": 0,
        "netLongsClose": -2465256,
        "netLongsLow": -2465256,
        "netShortsOpen": null,
        "netShortsClose": -137203,
        "netShortsHigh": 222704,
        "netShortsLow": -214512
    },
    {
        "id": null,
        "exchangeName": null,
        "symbol": null,
        "baseCoin": null,
        "begin": 1733796900000,
        "interval": "15m",
        "netLongsOpen": null,
        "netLongsHigh": 0,
        "netLongsClose": -2691910,
        "netLongsLow": -2691910,
        "netShortsOpen": null,
        "netShortsClose": -1794265,
        "netShortsHigh": 0,
        "netShortsLow": -2309029
    },
    {
        "id": null,
        "exchangeName": null,
        "symbol": null,
        "baseCoin": null,
        "begin": 1733797800000,
        "interval": "15m",
        "netLongsOpen": null,
        "netLongsHigh": 0,
        "netLongsClose": -1214308,
        "netLongsLow": -1744544,
        "netShortsOpen": null,
        "netShortsClose": 2766396,
        "netShortsHigh": 3060376,
        "netShortsLow": 0
    },
    {
        "id": null,
        "exchangeName": null,
        "symbol": null,
        "baseCoin": null,
        "begin": 1733798700000,
        "interval": "15m",
        "netLongsOpen": null,
        "netLongsHigh": 4686,
        "netLongsClose": -860098,
        "netLongsLow": -860098,
        "netShortsOpen": null,
        "netShortsClose": -526946,
        "netShortsHigh": 0,
        "netShortsLow": -567305
    },
    {
        "id": null,
        "exchangeName": null,
        "symbol": null,
        "baseCoin": null,
        "begin": 1733799600000,
        "interval": "15m",
        "netLongsOpen": null,
        "netLongsHigh": 270254,
        "netLongsClose": -4148820,
        "netLongsLow": -4148820,
        "netShortsOpen": null,
        "netShortsClose": 8489481,
        "netShortsHigh": 8489481,
        "netShortsLow": -225747
    },
    {
        "id": null,
        "exchangeName": null,
        "symbol": null,
        "baseCoin": null,
        "begin": 1733800500000,
        "interval": "15m",
        "netLongsOpen": null,
        "netLongsHigh": 299670,
        "netLongsClose": 299670,
        "netLongsLow": -655564,
        "netShortsOpen": null,
        "netShortsClose": -2520563,
        "netShortsHigh": 963648,
        "netShortsLow": -2520563
    },
    {
        "id": null,
        "exchangeName": null,
        "symbol": null,
        "baseCoin": null,
        "begin": 1733801400000,
        "interval": "15m",
        "netLongsOpen": null,
        "netLongsHigh": 1233142,
        "netLongsClose": 964322,
        "netLongsLow": 0,
        "netShortsOpen": null,
        "netShortsClose": -5931,
        "netShortsHigh": 601168,
        "netShortsLow": -38692
    },
    {
        "id": null,
        "exchangeName": null,
        "symbol": null,
        "baseCoin": null,
        "begin": 1733802300000,
        "interval": "15m",
        "netLongsOpen": null,
        "netLongsHigh": 869627,
        "netLongsClose": 723927,
        "netLongsLow": 0,
        "netShortsOpen": null,
        "netShortsClose": -1441795,
        "netShortsHigh": 0,
        "netShortsLow": -1441795
    },
    {
        "id": null,
        "exchangeName": null,
        "symbol": null,
        "baseCoin": null,
        "begin": 1733803200000,
        "interval": "15m",
        "netLongsOpen": null,
        "netLongsHigh": 0,
        "netLongsClose": -940077,
        "netLongsLow": -940077,
        "netShortsOpen": null,
        "netShortsClose": -689916,
        "netShortsHigh": 202883,
        "netShortsLow": -689916
    },
    {
        "id": null,
        "exchangeName": null,
        "symbol": null,
        "baseCoin": null,
        "begin": 1733804100000,
        "interval": "15m",
        "netLongsOpen": null,
        "netLongsHigh": 1066370,
        "netLongsClose": 1066370,
        "netLongsLow": -299028,
        "netShortsOpen": null,
        "netShortsClose": 1116670,
        "netShortsHigh": 1116670,
        "netShortsLow": 0
    },
    {
        "id": null,
        "exchangeName": null,
        "symbol": null,
        "baseCoin": null,
        "begin": 1733805000000,
        "interval": "15m",
        "netLongsOpen": null,
        "netLongsHigh": 284545,
        "netLongsClose": 52381,
        "netLongsLow": -299293,
        "netShortsOpen": null,
        "netShortsClose": -137567,
        "netShortsHigh": 412064,
        "netShortsLow": -137567
    },
    {
        "id": null,
        "exchangeName": null,
        "symbol": null,
        "baseCoin": null,
        "begin": 1733805900000,
        "interval": "15m",
        "netLongsOpen": null,
        "netLongsHigh": 579294,
        "netLongsClose": 579294,
        "netLongsLow": -671981,
        "netShortsOpen": null,
        "netShortsClose": -1397035,
        "netShortsHigh": 848850,
        "netShortsLow": -1397035
    },
    {
        "id": null,
        "exchangeName": null,
        "symbol": null,
        "baseCoin": null,
        "begin": 1733806800000,
        "interval": "15m",
        "netLongsOpen": null,
        "netLongsHigh": 1117332,
        "netLongsClose": 1117332,
        "netLongsLow": -1217870,
        "netShortsOpen": null,
        "netShortsClose": 1677870,
        "netShortsHigh": 1718898,
        "netShortsLow": 0
    },
    {
        "id": null,
        "exchangeName": null,
        "symbol": null,
        "baseCoin": null,
        "begin": 1733807700000,
        "interval": "15m",
        "netLongsOpen": null,
        "netLongsHigh": 239604,
        "netLongsClose": -18409,
        "netLongsLow": -589967,
        "netShortsOpen": null,
        "netShortsClose": -827956,
        "netShortsHigh": 144716,
        "netShortsLow": -827956
    },
    {
        "id": null,
        "exchangeName": null,
        "symbol": null,
        "baseCoin": null,
        "begin": 1733808600000,
        "interval": "15m",
        "netLongsOpen": null,
        "netLongsHigh": 979008,
        "netLongsClose": 49369,
        "netLongsLow": 0,
        "netShortsOpen": null,
        "netShortsClose": -690008,
        "netShortsHigh": 44385,
        "netShortsLow": -690008
    },
    {
        "id": null,
        "exchangeName": null,
        "symbol": null,
        "baseCoin": null,
        "begin": 1733809500000,
        "interval": "15m",
        "netLongsOpen": null,
        "netLongsHigh": 820588,
        "netLongsClose": 706360,
        "netLongsLow": -45051,
        "netShortsOpen": null,
        "netShortsClose": -1037791,
        "netShortsHigh": 0,
        "netShortsLow": -1037791
    },
    {
        "id": null,
        "exchangeName": null,
        "symbol": null,
        "baseCoin": null,
        "begin": 1733810400000,
        "interval": "15m",
        "netLongsOpen": null,
        "netLongsHigh": 117659,
        "netLongsClose": -254161,
        "netLongsLow": -713933,
        "netShortsOpen": null,
        "netShortsClose": -2745343,
        "netShortsHigh": 0,
        "netShortsLow": -2745343
    },
    {
        "id": null,
        "exchangeName": null,
        "symbol": null,
        "baseCoin": null,
        "begin": 1733811300000,
        "interval": "15m",
        "netLongsOpen": null,
        "netLongsHigh": 375065,
        "netLongsClose": 375065,
        "netLongsLow": -158289,
        "netShortsOpen": null,
        "netShortsClose": -925080,
        "netShortsHigh": 0,
        "netShortsLow": -925080
    },
    {
        "id": null,
        "exchangeName": null,
        "symbol": null,
        "baseCoin": null,
        "begin": 1733812200000,
        "interval": "15m",
        "netLongsOpen": null,
        "netLongsHigh": 497869,
        "netLongsClose": -123760,
        "netLongsLow": -123760,
        "netShortsOpen": null,
        "netShortsClose": -817569,
        "netShortsHigh": 0,
        "netShortsLow": -817569
    },
    {
        "id": null,
        "exchangeName": null,
        "symbol": null,
        "baseCoin": null,
        "begin": 1733813100000,
        "interval": "15m",
        "netLongsOpen": null,
        "netLongsHigh": 66598,
        "netLongsClose": -776212,
        "netLongsLow": -776212,
        "netShortsOpen": null,
        "netShortsClose": 233332,
        "netShortsHigh": 233332,
        "netShortsLow": -112324
    },
    {
        "id": null,
        "exchangeName": null,
        "symbol": null,
        "baseCoin": null,
        "begin": 1733814000000,
        "interval": "15m",
        "netLongsOpen": null,
        "netLongsHigh": 155704,
        "netLongsClose": -2405025,
        "netLongsLow": -2405025,
        "netShortsOpen": null,
        "netShortsClose": 463338,
        "netShortsHigh": 463338,
        "netShortsLow": -144306
    },
    {
        "id": null,
        "exchangeName": null,
        "symbol": null,
        "baseCoin": null,
        "begin": 1733814900000,
        "interval": "15m",
        "netLongsOpen": null,
        "netLongsHigh": 282562,
        "netLongsClose": 282562,
        "netLongsLow": -24291,
        "netShortsOpen": null,
        "netShortsClose": -370435,
        "netShortsHigh": 127241,
        "netShortsLow": -370435
    },
    {
        "id": null,
        "exchangeName": null,
        "symbol": null,
        "baseCoin": null,
        "begin": 1733815800000,
        "interval": "15m",
        "netLongsOpen": null,
        "netLongsHigh": 236152,
        "netLongsClose": 175386,
        "netLongsLow": -559824,
        "netShortsOpen": null,
        "netShortsClose": -484296,
        "netShortsHigh": 17117,
        "netShortsLow": -484296
    },
    {
        "id": null,
        "exchangeName": null,
        "symbol": null,
        "baseCoin": null,
        "begin": 1733816700000,
        "interval": "15m",
        "netLongsOpen": null,
        "netLongsHigh": 653330,
        "netLongsClose": 653330,
        "netLongsLow": -95580,
        "netShortsOpen": null,
        "netShortsClose": -1956484,
        "netShortsHigh": 0,
        "netShortsLow": -1956484
    },
    {
        "id": null,
        "exchangeName": null,
        "symbol": null,
        "baseCoin": null,
        "begin": 1733817600000,
        "interval": "15m",
        "netLongsOpen": null,
        "netLongsHigh": 7471214,
        "netLongsClose": 7471214,
        "netLongsLow": -1534357,
        "netShortsOpen": null,
        "netShortsClose": -789176,
        "netShortsHigh": 1114174,
        "netShortsLow": -789176
    },
    {
        "id": null,
        "exchangeName": null,
        "symbol": null,
        "baseCoin": null,
        "begin": 1733818500000,
        "interval": "15m",
        "netLongsOpen": null,
        "netLongsHigh": 1909357,
        "netLongsClose": 1909357,
        "netLongsLow": 0,
        "netShortsOpen": null,
        "netShortsClose": -1535272,
        "netShortsHigh": 0,
        "netShortsLow": -1535272
    },
    {
        "id": null,
        "exchangeName": null,
        "symbol": null,
        "baseCoin": null,
        "begin": 1733819400000,
        "interval": "15m",
        "netLongsOpen": null,
        "netLongsHigh": 1015496,
        "netLongsClose": -456272,
        "netLongsLow": -456272,
        "netShortsOpen": null,
        "netShortsClose": -2060086,
        "netShortsHigh": 0,
        "netShortsLow": -2413506
    },
    {
        "id": null,
        "exchangeName": null,
        "symbol": null,
        "baseCoin": null,
        "begin": 1733820300000,
        "interval": "15m",
        "netLongsOpen": null,
        "netLongsHigh": 1117752,
        "netLongsClose": -216879,
        "netLongsLow": -216879,
        "netShortsOpen": null,
        "netShortsClose": 1680701,
        "netShortsHigh": 1680701,
        "netShortsLow": -226718
    },
    {
        "id": null,
        "exchangeName": null,
        "symbol": null,
        "baseCoin": null,
        "begin": 1733821200000,
        "interval": "15m",
        "netLongsOpen": null,
        "netLongsHigh": 750660,
        "netLongsClose": 750660,
        "netLongsLow": -527388,
        "netShortsOpen": null,
        "netShortsClose": -351492,
        "netShortsHigh": 301601,
        "netShortsLow": -351492
    },
    {
        "id": null,
        "exchangeName": null,
        "symbol": null,
        "baseCoin": null,
        "begin": 1733822100000,
        "interval": "15m",
        "netLongsOpen": null,
        "netLongsHigh": 592458,
        "netLongsClose": -274903,
        "netLongsLow": -319225,
        "netShortsOpen": null,
        "netShortsClose": 51926,
        "netShortsHigh": 598038,
        "netShortsLow": 0
    },
    {
        "id": null,
        "exchangeName": null,
        "symbol": null,
        "baseCoin": null,
        "begin": 1733823000000,
        "interval": "15m",
        "netLongsOpen": null,
        "netLongsHigh": 1826998,
        "netLongsClose": -264988,
        "netLongsLow": -264988,
        "netShortsOpen": null,
        "netShortsClose": -2333901,
        "netShortsHigh": 96584,
        "netShortsLow": -2333901
    },
    {
        "id": null,
        "exchangeName": null,
        "symbol": null,
        "baseCoin": null,
        "begin": 1733823900000,
        "interval": "15m",
        "netLongsOpen": null,
        "netLongsHigh": 593369,
        "netLongsClose": -1030435,
        "netLongsLow": -1030435,
        "netShortsOpen": null,
        "netShortsClose": 528112,
        "netShortsHigh": 528112,
        "netShortsLow": -440609
    },
    {
        "id": null,
        "exchangeName": null,
        "symbol": null,
        "baseCoin": null,
        "begin": 1733824800000,
        "interval": "15m",
        "netLongsOpen": null,
        "netLongsHigh": 0,
        "netLongsClose": -1336488,
        "netLongsLow": -1336488,
        "netShortsOpen": null,
        "netShortsClose": 243503,
        "netShortsHigh": 269121,
        "netShortsLow": -273770
    },
    {
        "id": null,
        "exchangeName": null,
        "symbol": null,
        "baseCoin": null,
        "begin": 1733825700000,
        "interval": "15m",
        "netLongsOpen": null,
        "netLongsHigh": 180845,
        "netLongsClose": -624194,
        "netLongsLow": -624194,
        "netShortsOpen": null,
        "netShortsClose": 599768,
        "netShortsHigh": 599768,
        "netShortsLow": 0
    },
    {
        "id": null,
        "exchangeName": null,
        "symbol": null,
        "baseCoin": null,
        "begin": 1733826600000,
        "interval": "15m",
        "netLongsOpen": null,
        "netLongsHigh": 276091,
        "netLongsClose": 45539,
        "netLongsLow": -59271,
        "netShortsOpen": null,
        "netShortsClose": 122395,
        "netShortsHigh": 122395,
        "netShortsLow": -189427
    },
    {
        "id": null,
        "exchangeName": null,
        "symbol": null,
        "baseCoin": null,
        "begin": 1733827500000,
        "interval": "15m",
        "netLongsOpen": null,
        "netLongsHigh": 0,
        "netLongsClose": -738745,
        "netLongsLow": -738745,
        "netShortsOpen": null,
        "netShortsClose": -20493,
        "netShortsHigh": 134505,
        "netShortsLow": -20493
    },
    {
        "id": null,
        "exchangeName": null,
        "symbol": null,
        "baseCoin": null,
        "begin": 1733828400000,
        "interval": "15m",
        "netLongsOpen": null,
        "netLongsHigh": 122230,
        "netLongsClose": -1858323,
        "netLongsLow": -1858323,
        "netShortsOpen": null,
        "netShortsClose": 208329,
        "netShortsHigh": 208329,
        "netShortsLow": -490180
    },
    {
        "id": null,
        "exchangeName": null,
        "symbol": null,
        "baseCoin": null,
        "begin": 1733829300000,
        "interval": "15m",
        "netLongsOpen": null,
        "netLongsHigh": 0,
        "netLongsClose": -954478,
        "netLongsLow": -1139559,
        "netShortsOpen": null,
        "netShortsClose": 496615,
        "netShortsHigh": 1035367,
        "netShortsLow": 0
    },
    {
        "id": null,
        "exchangeName": null,
        "symbol": null,
        "baseCoin": null,
        "begin": 1733830200000,
        "interval": "15m",
        "netLongsOpen": null,
        "netLongsHigh": 144501,
        "netLongsClose": -1459058,
        "netLongsLow": -1459058,
        "netShortsOpen": null,
        "netShortsClose": 1291085,
        "netShortsHigh": 1291085,
        "netShortsLow": -352876
    },
    {
        "id": null,
        "exchangeName": null,
        "symbol": null,
        "baseCoin": null,
        "begin": 1733831100000,
        "interval": "15m",
        "netLongsOpen": null,
        "netLongsHigh": 76507,
        "netLongsClose": -140456,
        "netLongsLow": -286853,
        "netShortsOpen": null,
        "netShortsClose": -837031,
        "netShortsHigh": 0,
        "netShortsLow": -837031
    },
    {
        "id": null,
        "exchangeName": null,
        "symbol": null,
        "baseCoin": null,
        "begin": 1733832000000,
        "interval": "15m",
        "netLongsOpen": null,
        "netLongsHigh": 48453,
        "netLongsClose": -2213688,
        "netLongsLow": -2213688,
        "netShortsOpen": null,
        "netShortsClose": 837974,
        "netShortsHigh": 837974,
        "netShortsLow": -223457
    },
    {
        "id": null,
        "exchangeName": null,
        "symbol": null,
        "baseCoin": null,
        "begin": 1733832900000,
        "interval": "15m",
        "netLongsOpen": null,
        "netLongsHigh": 749645,
        "netLongsClose": 749645,
        "netLongsLow": -952804,
        "netShortsOpen": null,
        "netShortsClose": 1111925,
        "netShortsHigh": 1111925,
        "netShortsLow": -297239
    },
    {
        "id": null,
        "exchangeName": null,
        "symbol": null,
        "baseCoin": null,
        "begin": 1733833800000,
        "interval": "15m",
        "netLongsOpen": null,
        "netLongsHigh": 416496,
        "netLongsClose": -2155525,
        "netLongsLow": -2155525,
        "netShortsOpen": null,
        "netShortsClose": 2828213,
        "netShortsHigh": 2828213,
        "netShortsLow": -234459
    },
    {
        "id": null,
        "exchangeName": null,
        "symbol": null,
        "baseCoin": null,
        "begin": 1733834700000,
        "interval": "15m",
        "netLongsOpen": null,
        "netLongsHigh": 709665,
        "netLongsClose": -422571,
        "netLongsLow": -422571,
        "netShortsOpen": null,
        "netShortsClose": 459382,
        "netShortsHigh": 647283,
        "netShortsLow": 0
    },
    {
        "id": null,
        "exchangeName": null,
        "symbol": null,
        "baseCoin": null,
        "begin": 1733835600000,
        "interval": "15m",
        "netLongsOpen": null,
        "netLongsHigh": 4492577,
        "netLongsClose": 4289538,
        "netLongsLow": 0,
        "netShortsOpen": null,
        "netShortsClose": 220771,
        "netShortsHigh": 220771,
        "netShortsLow": -681045
    },
    {
        "id": null,
        "exchangeName": null,
        "symbol": null,
        "baseCoin": null,
        "begin": 1733836500000,
        "interval": "15m",
        "netLongsOpen": null,
        "netLongsHigh": 0,
        "netLongsClose": -1133098,
        "netLongsLow": -1133098,
        "netShortsOpen": null,
        "netShortsClose": -781885,
        "netShortsHigh": 279947,
        "netShortsLow": -781885
    },
    {
        "id": null,
        "exchangeName": null,
        "symbol": null,
        "baseCoin": null,
        "begin": 1733837400000,
        "interval": "15m",
        "netLongsOpen": null,
        "netLongsHigh": 1879930,
        "netLongsClose": 1879930,
        "netLongsLow": 0,
        "netShortsOpen": null,
        "netShortsClose": -148894,
        "netShortsHigh": 0,
        "netShortsLow": -640593
    },
    {
        "id": null,
        "exchangeName": null,
        "symbol": null,
        "baseCoin": null,
        "begin": 1733838300000,
        "interval": "15m",
        "netLongsOpen": null,
        "netLongsHigh": 431541,
        "netLongsClose": -314109,
        "netLongsLow": -461201,
        "netShortsOpen": null,
        "netShortsClose": 371578,
        "netShortsHigh": 542264,
        "netShortsLow": -47299
    },
    {
        "id": null,
        "exchangeName": null,
        "symbol": null,
        "baseCoin": null,
        "begin": 1733839200000,
        "interval": "15m",
        "netLongsOpen": null,
        "netLongsHigh": 942186,
        "netLongsClose": 449820,
        "netLongsLow": 0,
        "netShortsOpen": null,
        "netShortsClose": 612856,
        "netShortsHigh": 612856,
        "netShortsLow": -611749
    },
    {
        "id": null,
        "exchangeName": null,
        "symbol": null,
        "baseCoin": null,
        "begin": 1733840100000,
        "interval": "15m",
        "netLongsOpen": null,
        "netLongsHigh": 1564653,
        "netLongsClose": 1564653,
        "netLongsLow": -1893282,
        "netShortsOpen": null,
        "netShortsClose": -632511,
        "netShortsHigh": 91082,
        "netShortsLow": -632511
    },
    {
        "id": null,
        "exchangeName": null,
        "symbol": null,
        "baseCoin": null,
        "begin": 1733841000000,
        "interval": "15m",
        "netLongsOpen": null,
        "netLongsHigh": 0,
        "netLongsClose": -1696955,
        "netLongsLow": -2851616,
        "netShortsOpen": null,
        "netShortsClose": -781876,
        "netShortsHigh": 0,
        "netShortsLow": -781876
    },
    {
        "id": null,
        "exchangeName": null,
        "symbol": null,
        "baseCoin": null,
        "begin": 1733841900000,
        "interval": "15m",
        "netLongsOpen": null,
        "netLongsHigh": 845377,
        "netLongsClose": -1624450,
        "netLongsLow": -1624450,
        "netShortsOpen": null,
        "netShortsClose": -103588,
        "netShortsHigh": 872920,
        "netShortsLow": -103588
    },
    {
        "id": null,
        "exchangeName": null,
        "symbol": null,
        "baseCoin": null,
        "begin": 1733842800000,
        "interval": "15m",
        "netLongsOpen": null,
        "netLongsHigh": 123723,
        "netLongsClose": -344554,
        "netLongsLow": -351958,
        "netShortsOpen": null,
        "netShortsClose": -501485,
        "netShortsHigh": 445375,
        "netShortsLow": -501485
    },
    {
        "id": null,
        "exchangeName": null,
        "symbol": null,
        "baseCoin": null,
        "begin": 1733843700000,
        "interval": "15m",
        "netLongsOpen": null,
        "netLongsHigh": 24402,
        "netLongsClose": -5282286,
        "netLongsLow": -5282286,
        "netShortsOpen": null,
        "netShortsClose": 1227487,
        "netShortsHigh": 2058762,
        "netShortsLow": 0
    },
    {
        "id": null,
        "exchangeName": null,
        "symbol": null,
        "baseCoin": null,
        "begin": 1733844600000,
        "interval": "15m",
        "netLongsOpen": null,
        "netLongsHigh": 372190,
        "netLongsClose": -1371295,
        "netLongsLow": -1371295,
        "netShortsOpen": null,
        "netShortsClose": 1664231,
        "netShortsHigh": 1898347,
        "netShortsLow": 0
    },
    {
        "id": null,
        "exchangeName": null,
        "symbol": null,
        "baseCoin": null,
        "begin": 1733845500000,
        "interval": "15m",
        "netLongsOpen": null,
        "netLongsHigh": 481142,
        "netLongsClose": 97991,
        "netLongsLow": -66419,
        "netShortsOpen": null,
        "netShortsClose": 364178,
        "netShortsHigh": 364178,
        "netShortsLow": -944455
    }
]