[
    {
        "t": 1734883200,
        "l": 31.74552,
        "s": 0
    },
    {
        "t": 1734884100,
        "l": 1080.3573000000001,
        "s": 10217.90968
    },
    {
        "t": 1734885000,
        "l": 0.7548,
        "s": 0
    },
    {
        "t": 1734889500,
        "l": 1612.27839,
        "s": 0
    },
    {
        "t": 1734890400,
        "l": 906.47064,
        "s": 6.65364
    },
    {
        "t": 1734892200,
        "l": 0,
        "s": 9718.55865
    },
    {
        "t": 1734894000,
        "l": 38786.40857,
        "s": 0
    },
    {
        "t": 1734894900,
        "l": 686.4848300000001,
        "s": 0
    },
    {
        "t": 1734895800,
        "l": 3582.0939700000004,
        "s": 0
    },
    {
        "t": 1734896700,
        "l": 36099.1476,
        "s": 0
    },
    {
        "t": 1734897600,
        "l": 178507.83951,
        "s": 0
    },
    {
        "t": 1734898500,
        "l": 0,
        "s": 2476.38424
    },
    {
        "t": 1734899400,
        "l": 0,
        "s": 1119.8370400000001
    },
    {
        "t": 1734900300,
        "l": 0,
        "s": 10716.1408
    },
    {
        "t": 1734901200,
        "l": 0,
        "s": 3062.53068
    },
    {
        "t": 1734902100,
        "l": 0,
        "s": 8808.825239999998
    },
    {
        "t": 1734903900,
        "l": 23.835679999999996,
        "s": 0
    },
    {
        "t": 1734904800,
        "l": 13823.42474,
        "s": 160.84716
    },
    {
        "t": 1734908400,
        "l": 0,
        "s": 355.4278
    },
    {
        "t": 1734909300,
        "l": 711.1805999999999,
        "s": 0
    },
    {
        "t": 1734910200,
        "l": 809.5855399999998,
        "s": 0
    },
    {
        "t": 1734912000,
        "l": 36485.1744,
        "s": 0
    },
    {
        "t": 1734912900,
        "l": 21993.314819999996,
        "s": 0
    },
    {
        "t": 1734913800,
        "l": 4209.8867,
        "s": 0
    },
    {
        "t": 1734914700,
        "l": 308.12750000000005,
        "s": 0
    },
    {
        "t": 1734915600,
        "l": 6173.543610000001,
        "s": 0
    },
    {
        "t": 1734916500,
        "l": 11664.357059999998,
        "s": 0
    },
    {
        "t": 1734917400,
        "l": 0,
        "s": 9.90318
    },
    {
        "t": 1734919200,
        "l": 42874.86005,
        "s": 0
    },
    {
        "t": 1734920100,
        "l": 11.776,
        "s": 0
    },
    {
        "t": 1734921900,
        "l": 0,
        "s": 768.04726
    },
    {
        "t": 1734922800,
        "l": 174.34,
        "s": 1664.8345
    },
    {
        "t": 1734923700,
        "l": 0,
        "s": 45884.66364
    },
    {
        "t": 1734924600,
        "l": 0,
        "s": 30.917820000000003
    },
    {
        "t": 1734925500,
        "l": 0,
        "s": 397.90422
    },
    {
        "t": 1734926400,
        "l": 0,
        "s": 208.25483999999997
    },
    {
        "t": 1734927300,
        "l": 0,
        "s": 516.42228
    },
    {
        "t": 1734928200,
        "l": 4325.8248300000005,
        "s": 0
    },
    {
        "t": 1734929100,
        "l": 235.20207000000002,
        "s": 0
    },
    {
        "t": 1734930900,
        "l": 118.69804000000002,
        "s": 0
    },
    {
        "t": 1734933600,
        "l": 5011.509209999999,
        "s": 0
    },
    {
        "t": 1734935400,
        "l": 11011.155299999999,
        "s": 0
    },
    {
        "t": 1734938100,
        "l": 0,
        "s": 42.778499999999994
    },
    {
        "t": 1734939900,
        "l": 0,
        "s": 3410.1897599999998
    },
    {
        "t": 1734940800,
        "l": 0,
        "s": 449.11082000000005
    },
    {
        "t": 1734944400,
        "l": 0,
        "s": 2764.3117199999997
    },
    {
        "t": 1734948900,
        "l": 93.87747999999999,
        "s": 0
    },
    {
        "t": 1734949800,
        "l": 395.42175,
        "s": 0
    },
    {
        "t": 1734950700,
        "l": 3083.7051599999995,
        "s": 0
    },
    {
        "t": 1734954300,
        "l": 1584.3603999999998,
        "s": 0
    },
    {
        "t": 1734957900,
        "l": 0,
        "s": 389.35275
    },
    {
        "t": 1734958800,
        "l": 1369.5209599999998,
        "s": 0
    },
    {
        "t": 1734960600,
        "l": 2659.3684200000002,
        "s": 0
    },
    {
        "t": 1734962400,
        "l": 0,
        "s": 5478.85659
    },
    {
        "t": 1734964200,
        "l": 23575.39333,
        "s": 0
    },
    {
        "t": 1734965100,
        "l": 210168.36919,
        "s": 0
    },
    {
        "t": 1734968700,
        "l": 824.69486,
        "s": 0
    }
]