[
    {
        "t": 1735404300,
        "l": 0,
        "s": 56175.1662
    },
    {
        "t": 1735405200,
        "l": 0,
        "s": 36686.1702
    },
    {
        "t": 1735406100,
        "l": 6.7964,
        "s": 30045.8414
    },
    {
        "t": 1735409700,
        "l": 70.4344,
        "s": 0
    },
    {
        "t": 1735410600,
        "l": 1655.402,
        "s": 0
    },
    {
        "t": 1735411500,
        "l": 197.6448,
        "s": 0
    },
    {
        "t": 1735412400,
        "l": 2318.4,
        "s": 0
    },
    {
        "t": 1735416000,
        "l": 7.21,
        "s": 0
    },
    {
        "t": 1735422300,
        "l": 0,
        "s": 1563.5904
    },
    {
        "t": 1735423200,
        "l": 0,
        "s": 592.007
    },
    {
        "t": 1735425900,
        "l": 0,
        "s": 6904.0026
    },
    {
        "t": 1735428600,
        "l": 4923.0258,
        "s": 0
    },
    {
        "t": 1735433100,
        "l": 1022.627,
        "s": 0
    },
    {
        "t": 1735434000,
        "l": 8405.9874,
        "s": 0
    },
    {
        "t": 1735434900,
        "l": 8252.2186,
        "s": 0
    },
    {
        "t": 1735442100,
        "l": 133.4892,
        "s": 0
    },
    {
        "t": 1735452000,
        "l": 7339.919999999999,
        "s": 0
    },
    {
        "t": 1735462800,
        "l": 61.715999999999994,
        "s": 0
    },
    {
        "t": 1735463700,
        "l": 1998.588,
        "s": 0
    },
    {
        "t": 1735465500,
        "l": 972.5088000000001,
        "s": 0
    },
    {
        "t": 1735469100,
        "l": 11044.076100000002,
        "s": 0
    },
    {
        "t": 1735470000,
        "l": 8401.634,
        "s": 0
    },
    {
        "t": 1735470900,
        "l": 9433.398799999999,
        "s": 0
    },
    {
        "t": 1735475400,
        "l": 20778.0018,
        "s": 0
    },
    {
        "t": 1735474500,
        "l": 604.5728000000001,
        "s": 0
    },
    {
        "t": 1735473600,
        "l": 909.2132,
        "s": 0
    },
    {
        "t": 1735478100,
        "l": 1.5360000000000003,
        "s": 381.3655
    },
    {
        "t": 1735480800,
        "l": 0,
        "s": 11081.1515
    },
    {
        "t": 1735481700,
        "l": 3383.3508,
        "s": 0
    },
    {
        "t": 1735482600,
        "l": 34637.9151,
        "s": 0
    },
    {
        "t": 1735483500,
        "l": 4302.1644,
        "s": 396.86400000000003
    },
    {
        "t": 1735486200,
        "l": 0,
        "s": 4252.7516000000005
    }
]