[
    {
        "id": null,
        "exchangeName": null,
        "symbol": null,
        "baseCoin": null,
        "begin": 1734364800000,
        "interval": "15m",
        "netLongsOpen": null,
        "netLongsHigh": 4156,
        "netLongsClose": 4156,
        "netLongsLow": -5,
        "netShortsOpen": null,
        "netShortsClose": 1305,
        "netShortsHigh": 1500,
        "netShortsLow": -322
    },
    {
        "id": null,
        "exchangeName": null,
        "symbol": null,
        "baseCoin": null,
        "begin": 1734365700000,
        "interval": "15m",
        "netLongsOpen": null,
        "netLongsHigh": 735,
        "netLongsClose": -1587,
        "netLongsLow": -1943,
        "netShortsOpen": null,
        "netShortsClose": 1520,
        "netShortsHigh": 1520,
        "netShortsLow": -992
    },
    {
        "id": null,
        "exchangeName": null,
        "symbol": null,
        "baseCoin": null,
        "begin": 1734366600000,
        "interval": "15m",
        "netLongsOpen": null,
        "netLongsHigh": 5860,
        "netLongsClose": 5860,
        "netLongsLow": 0,
        "netShortsOpen": null,
        "netShortsClose": -718,
        "netShortsHigh": 186,
        "netShortsLow": -1960
    },
    {
        "id": null,
        "exchangeName": null,
        "symbol": null,
        "baseCoin": null,
        "begin": 1734367500000,
        "interval": "15m",
        "netLongsOpen": null,
        "netLongsHigh": 0,
        "netLongsClose": -12345,
        "netLongsLow": -12345,
        "netShortsOpen": null,
        "netShortsClose": 4202,
        "netShortsHigh": 4266,
        "netShortsLow": 0
    },
    {
        "id": null,
        "exchangeName": null,
        "symbol": null,
        "baseCoin": null,
        "begin": 1734368400000,
        "interval": "15m",
        "netLongsOpen": null,
        "netLongsHigh": 4682,
        "netLongsClose": 4682,
        "netLongsLow": -182,
        "netShortsOpen": null,
        "netShortsClose": -9941,
        "netShortsHigh": 193,
        "netShortsLow": -9941
    },
    {
        "id": null,
        "exchangeName": null,
        "symbol": null,
        "baseCoin": null,
        "begin": 1734369300000,
        "interval": "15m",
        "netLongsOpen": null,
        "netLongsHigh": 13511,
        "netLongsClose": 13511,
        "netLongsLow": -343,
        "netShortsOpen": null,
        "netShortsClose": -12995,
        "netShortsHigh": 32,
        "netShortsLow": -12995
    },
    {
        "id": null,
        "exchangeName": null,
        "symbol": null,
        "baseCoin": null,
        "begin": 1734370200000,
        "interval": "15m",
        "netLongsOpen": null,
        "netLongsHigh": 0,
        "netLongsClose": -8087,
        "netLongsLow": -8087,
        "netShortsOpen": null,
        "netShortsClose": -1002,
        "netShortsHigh": 0,
        "netShortsLow": -5227
    },
    {
        "id": null,
        "exchangeName": null,
        "symbol": null,
        "baseCoin": null,
        "begin": 1734371100000,
        "interval": "15m",
        "netLongsOpen": null,
        "netLongsHigh": 0,
        "netLongsClose": -21965,
        "netLongsLow": -21965,
        "netShortsOpen": null,
        "netShortsClose": 5109,
        "netShortsHigh": 5748,
        "netShortsLow": -3077
    },
    {
        "id": null,
        "exchangeName": null,
        "symbol": null,
        "baseCoin": null,
        "begin": 1734372000000,
        "interval": "15m",
        "netLongsOpen": null,
        "netLongsHigh": 6987,
        "netLongsClose": 4938,
        "netLongsLow": 0,
        "netShortsOpen": null,
        "netShortsClose": -3355,
        "netShortsHigh": 0,
        "netShortsLow": -4409
    },
    {
        "id": null,
        "exchangeName": null,
        "symbol": null,
        "baseCoin": null,
        "begin": 1734372900000,
        "interval": "15m",
        "netLongsOpen": null,
        "netLongsHigh": 3139,
        "netLongsClose": 3139,
        "netLongsLow": -395,
        "netShortsOpen": null,
        "netShortsClose": -1540,
        "netShortsHigh": 0,
        "netShortsLow": -1540
    },
    {
        "id": null,
        "exchangeName": null,
        "symbol": null,
        "baseCoin": null,
        "begin": 1734373800000,
        "interval": "15m",
        "netLongsOpen": null,
        "netLongsHigh": 0,
        "netLongsClose": -4747,
        "netLongsLow": -5207,
        "netShortsOpen": null,
        "netShortsClose": 3034,
        "netShortsHigh": 3580,
        "netShortsLow": 0
    },
    {
        "id": null,
        "exchangeName": null,
        "symbol": null,
        "baseCoin": null,
        "begin": 1734374700000,
        "interval": "15m",
        "netLongsOpen": null,
        "netLongsHigh": 2636,
        "netLongsClose": 2258,
        "netLongsLow": -508,
        "netShortsOpen": null,
        "netShortsClose": -188,
        "netShortsHigh": 1534,
        "netShortsLow": -234
    },
    {
        "id": null,
        "exchangeName": null,
        "symbol": null,
        "baseCoin": null,
        "begin": 1734375600000,
        "interval": "15m",
        "netLongsOpen": null,
        "netLongsHigh": 2647,
        "netLongsClose": -4526,
        "netLongsLow": -4526,
        "netShortsOpen": null,
        "netShortsClose": 6437,
        "netShortsHigh": 6437,
        "netShortsLow": 0
    },
    {
        "id": null,
        "exchangeName": null,
        "symbol": null,
        "baseCoin": null,
        "begin": 1734376500000,
        "interval": "15m",
        "netLongsOpen": null,
        "netLongsHigh": 0,
        "netLongsClose": -3889,
        "netLongsLow": -4871,
        "netShortsOpen": null,
        "netShortsClose": 2511,
        "netShortsHigh": 3512,
        "netShortsLow": -200
    },
    {
        "id": null,
        "exchangeName": null,
        "symbol": null,
        "baseCoin": null,
        "begin": 1734377400000,
        "interval": "15m",
        "netLongsOpen": null,
        "netLongsHigh": 838,
        "netLongsClose": 838,
        "netLongsLow": -1363,
        "netShortsOpen": null,
        "netShortsClose": -737,
        "netShortsHigh": 933,
        "netShortsLow": -888
    },
    {
        "id": null,
        "exchangeName": null,
        "symbol": null,
        "baseCoin": null,
        "begin": 1734378300000,
        "interval": "15m",
        "netLongsOpen": null,
        "netLongsHigh": 1296,
        "netLongsClose": 987,
        "netLongsLow": -926,
        "netShortsOpen": null,
        "netShortsClose": 150,
        "netShortsHigh": 940,
        "netShortsLow": -469
    },
    {
        "id": null,
        "exchangeName": null,
        "symbol": null,
        "baseCoin": null,
        "begin": 1734379200000,
        "interval": "15m",
        "netLongsOpen": null,
        "netLongsHigh": 3076,
        "netLongsClose": 3076,
        "netLongsLow": -383,
        "netShortsOpen": null,
        "netShortsClose": -3185,
        "netShortsHigh": 0,
        "netShortsLow": -3185
    },
    {
        "id": null,
        "exchangeName": null,
        "symbol": null,
        "baseCoin": null,
        "begin": 1734380100000,
        "interval": "15m",
        "netLongsOpen": null,
        "netLongsHigh": 3538,
        "netLongsClose": 3538,
        "netLongsLow": 0,
        "netShortsOpen": null,
        "netShortsClose": -1814,
        "netShortsHigh": 142,
        "netShortsLow": -2397
    },
    {
        "id": null,
        "exchangeName": null,
        "symbol": null,
        "baseCoin": null,
        "begin": 1734381000000,
        "interval": "15m",
        "netLongsOpen": null,
        "netLongsHigh": 0,
        "netLongsClose": -1002,
        "netLongsLow": -2697,
        "netShortsOpen": null,
        "netShortsClose": 2894,
        "netShortsHigh": 2894,
        "netShortsLow": 0
    },
    {
        "id": null,
        "exchangeName": null,
        "symbol": null,
        "baseCoin": null,
        "begin": 1734381900000,
        "interval": "15m",
        "netLongsOpen": null,
        "netLongsHigh": 548,
        "netLongsClose": -1115,
        "netLongsLow": -3440,
        "netShortsOpen": null,
        "netShortsClose": 900,
        "netShortsHigh": 1011,
        "netShortsLow": -553
    },
    {
        "id": null,
        "exchangeName": null,
        "symbol": null,
        "baseCoin": null,
        "begin": 1734382800000,
        "interval": "15m",
        "netLongsOpen": null,
        "netLongsHigh": 2472,
        "netLongsClose": 2472,
        "netLongsLow": -60,
        "netShortsOpen": null,
        "netShortsClose": 1289,
        "netShortsHigh": 1289,
        "netShortsLow": -1669
    },
    {
        "id": null,
        "exchangeName": null,
        "symbol": null,
        "baseCoin": null,
        "begin": 1734383700000,
        "interval": "15m",
        "netLongsOpen": null,
        "netLongsHigh": 1226,
        "netLongsClose": -173,
        "netLongsLow": -173,
        "netShortsOpen": null,
        "netShortsClose": -2532,
        "netShortsHigh": 0,
        "netShortsLow": -2955
    },
    {
        "id": null,
        "exchangeName": null,
        "symbol": null,
        "baseCoin": null,
        "begin": 1734384600000,
        "interval": "15m",
        "netLongsOpen": null,
        "netLongsHigh": 2664,
        "netLongsClose": 2664,
        "netLongsLow": -736,
        "netShortsOpen": null,
        "netShortsClose": 124,
        "netShortsHigh": 805,
        "netShortsLow": -198
    },
    {
        "id": null,
        "exchangeName": null,
        "symbol": null,
        "baseCoin": null,
        "begin": 1734385500000,
        "interval": "15m",
        "netLongsOpen": null,
        "netLongsHigh": 21030,
        "netLongsClose": 21030,
        "netLongsLow": 0,
        "netShortsOpen": null,
        "netShortsClose": 1442,
        "netShortsHigh": 1442,
        "netShortsLow": -2579
    },
    {
        "id": null,
        "exchangeName": null,
        "symbol": null,
        "baseCoin": null,
        "begin": 1734386400000,
        "interval": "15m",
        "netLongsOpen": null,
        "netLongsHigh": 19,
        "netLongsClose": -627,
        "netLongsLow": -1837,
        "netShortsOpen": null,
        "netShortsClose": -2967,
        "netShortsHigh": 0,
        "netShortsLow": -2967
    },
    {
        "id": null,
        "exchangeName": null,
        "symbol": null,
        "baseCoin": null,
        "begin": 1734387300000,
        "interval": "15m",
        "netLongsOpen": null,
        "netLongsHigh": 0,
        "netLongsClose": -1651,
        "netLongsLow": -3167,
        "netShortsOpen": null,
        "netShortsClose": -1616,
        "netShortsHigh": 172,
        "netShortsLow": -1616
    },
    {
        "id": null,
        "exchangeName": null,
        "symbol": null,
        "baseCoin": null,
        "begin": 1734388200000,
        "interval": "15m",
        "netLongsOpen": null,
        "netLongsHigh": 0,
        "netLongsClose": -2158,
        "netLongsLow": -2523,
        "netShortsOpen": null,
        "netShortsClose": -532,
        "netShortsHigh": 0,
        "netShortsLow": -874
    },
    {
        "id": null,
        "exchangeName": null,
        "symbol": null,
        "baseCoin": null,
        "begin": 1734389100000,
        "interval": "15m",
        "netLongsOpen": null,
        "netLongsHigh": 1481,
        "netLongsClose": -1327,
        "netLongsLow": -1327,
        "netShortsOpen": null,
        "netShortsClose": 953,
        "netShortsHigh": 953,
        "netShortsLow": -1448
    },
    {
        "id": null,
        "exchangeName": null,
        "symbol": null,
        "baseCoin": null,
        "begin": 1734390000000,
        "interval": "15m",
        "netLongsOpen": null,
        "netLongsHigh": 427,
        "netLongsClose": -608,
        "netLongsLow": -1085,
        "netShortsOpen": null,
        "netShortsClose": 1346,
        "netShortsHigh": 2703,
        "netShortsLow": -83
    },
    {
        "id": null,
        "exchangeName": null,
        "symbol": null,
        "baseCoin": null,
        "begin": 1734390900000,
        "interval": "15m",
        "netLongsOpen": null,
        "netLongsHigh": 82,
        "netLongsClose": -6815,
        "netLongsLow": -6815,
        "netShortsOpen": null,
        "netShortsClose": 5408,
        "netShortsHigh": 5782,
        "netShortsLow": -85
    },
    {
        "id": null,
        "exchangeName": null,
        "symbol": null,
        "baseCoin": null,
        "begin": 1734391800000,
        "interval": "15m",
        "netLongsOpen": null,
        "netLongsHigh": 181,
        "netLongsClose": -1797,
        "netLongsLow": -4164,
        "netShortsOpen": null,
        "netShortsClose": 2776,
        "netShortsHigh": 5670,
        "netShortsLow": 0
    },
    {
        "id": null,
        "exchangeName": null,
        "symbol": null,
        "baseCoin": null,
        "begin": 1734392700000,
        "interval": "15m",
        "netLongsOpen": null,
        "netLongsHigh": 1444,
        "netLongsClose": -245,
        "netLongsLow": -245,
        "netShortsOpen": null,
        "netShortsClose": -381,
        "netShortsHigh": 0,
        "netShortsLow": -1121
    },
    {
        "id": null,
        "exchangeName": null,
        "symbol": null,
        "baseCoin": null,
        "begin": 1734393600000,
        "interval": "15m",
        "netLongsOpen": null,
        "netLongsHigh": 964,
        "netLongsClose": -4429,
        "netLongsLow": -7287,
        "netShortsOpen": null,
        "netShortsClose": 2255,
        "netShortsHigh": 2319,
        "netShortsLow": -1623
    },
    {
        "id": null,
        "exchangeName": null,
        "symbol": null,
        "baseCoin": null,
        "begin": 1734394500000,
        "interval": "15m",
        "netLongsOpen": null,
        "netLongsHigh": 3684,
        "netLongsClose": 1964,
        "netLongsLow": -396,
        "netShortsOpen": null,
        "netShortsClose": -3719,
        "netShortsHigh": 0,
        "netShortsLow": -3719
    },
    {
        "id": null,
        "exchangeName": null,
        "symbol": null,
        "baseCoin": null,
        "begin": 1734395400000,
        "interval": "15m",
        "netLongsOpen": null,
        "netLongsHigh": 2204,
        "netLongsClose": -2498,
        "netLongsLow": -2498,
        "netShortsOpen": null,
        "netShortsClose": -132,
        "netShortsHigh": 125,
        "netShortsLow": -875
    },
    {
        "id": null,
        "exchangeName": null,
        "symbol": null,
        "baseCoin": null,
        "begin": 1734396300000,
        "interval": "15m",
        "netLongsOpen": null,
        "netLongsHigh": 2844,
        "netLongsClose": 860,
        "netLongsLow": -1218,
        "netShortsOpen": null,
        "netShortsClose": -2811,
        "netShortsHigh": 0,
        "netShortsLow": -4779
    },
    {
        "id": null,
        "exchangeName": null,
        "symbol": null,
        "baseCoin": null,
        "begin": 1734397200000,
        "interval": "15m",
        "netLongsOpen": null,
        "netLongsHigh": 0,
        "netLongsClose": -5302,
        "netLongsLow": -11071,
        "netShortsOpen": null,
        "netShortsClose": 30844,
        "netShortsHigh": 30844,
        "netShortsLow": 0
    },
    {
        "id": null,
        "exchangeName": null,
        "symbol": null,
        "baseCoin": null,
        "begin": 1734398100000,
        "interval": "15m",
        "netLongsOpen": null,
        "netLongsHigh": 2768,
        "netLongsClose": 2071,
        "netLongsLow": -1354,
        "netShortsOpen": null,
        "netShortsClose": -1253,
        "netShortsHigh": 421,
        "netShortsLow": -5682
    },
    {
        "id": null,
        "exchangeName": null,
        "symbol": null,
        "baseCoin": null,
        "begin": 1734399000000,
        "interval": "15m",
        "netLongsOpen": null,
        "netLongsHigh": 5437,
        "netLongsClose": 5437,
        "netLongsLow": 0,
        "netShortsOpen": null,
        "netShortsClose": -906,
        "netShortsHigh": 417,
        "netShortsLow": -2191
    },
    {
        "id": null,
        "exchangeName": null,
        "symbol": null,
        "baseCoin": null,
        "begin": 1734399900000,
        "interval": "15m",
        "netLongsOpen": null,
        "netLongsHigh": 1767,
        "netLongsClose": 1239,
        "netLongsLow": 0,
        "netShortsOpen": null,
        "netShortsClose": 481,
        "netShortsHigh": 481,
        "netShortsLow": -462
    },
    {
        "id": null,
        "exchangeName": null,
        "symbol": null,
        "baseCoin": null,
        "begin": 1734400800000,
        "interval": "15m",
        "netLongsOpen": null,
        "netLongsHigh": 29169,
        "netLongsClose": 29169,
        "netLongsLow": -440,
        "netShortsOpen": null,
        "netShortsClose": -3851,
        "netShortsHigh": 299,
        "netShortsLow": -3851
    },
    {
        "id": null,
        "exchangeName": null,
        "symbol": null,
        "baseCoin": null,
        "begin": 1734401700000,
        "interval": "15m",
        "netLongsOpen": null,
        "netLongsHigh": 0,
        "netLongsClose": -2279,
        "netLongsLow": -3306,
        "netShortsOpen": null,
        "netShortsClose": -2872,
        "netShortsHigh": 0,
        "netShortsLow": -2872
    },
    {
        "id": null,
        "exchangeName": null,
        "symbol": null,
        "baseCoin": null,
        "begin": 1734402600000,
        "interval": "15m",
        "netLongsOpen": null,
        "netLongsHigh": 0,
        "netLongsClose": -1998,
        "netLongsLow": -3266,
        "netShortsOpen": null,
        "netShortsClose": 2823,
        "netShortsHigh": 2951,
        "netShortsLow": 0
    },
    {
        "id": null,
        "exchangeName": null,
        "symbol": null,
        "baseCoin": null,
        "begin": 1734403500000,
        "interval": "15m",
        "netLongsOpen": null,
        "netLongsHigh": 18648,
        "netLongsClose": 18648,
        "netLongsLow": -2201,
        "netShortsOpen": null,
        "netShortsClose": 3764,
        "netShortsHigh": 3764,
        "netShortsLow": -5405
    },
    {
        "id": null,
        "exchangeName": null,
        "symbol": null,
        "baseCoin": null,
        "begin": 1734404400000,
        "interval": "15m",
        "netLongsOpen": null,
        "netLongsHigh": 988,
        "netLongsClose": -2814,
        "netLongsLow": -2814,
        "netShortsOpen": null,
        "netShortsClose": 631,
        "netShortsHigh": 631,
        "netShortsLow": -628
    },
    {
        "id": null,
        "exchangeName": null,
        "symbol": null,
        "baseCoin": null,
        "begin": 1734405300000,
        "interval": "15m",
        "netLongsOpen": null,
        "netLongsHigh": 1453,
        "netLongsClose": 78,
        "netLongsLow": 0,
        "netShortsOpen": null,
        "netShortsClose": -840,
        "netShortsHigh": 92,
        "netShortsLow": -1504
    },
    {
        "id": null,
        "exchangeName": null,
        "symbol": null,
        "baseCoin": null,
        "begin": 1734406200000,
        "interval": "15m",
        "netLongsOpen": null,
        "netLongsHigh": 1094,
        "netLongsClose": 1094,
        "netLongsLow": -1062,
        "netShortsOpen": null,
        "netShortsClose": 117,
        "netShortsHigh": 338,
        "netShortsLow": -96
    },
    {
        "id": null,
        "exchangeName": null,
        "symbol": null,
        "baseCoin": null,
        "begin": 1734407100000,
        "interval": "15m",
        "netLongsOpen": null,
        "netLongsHigh": 1911,
        "netLongsClose": 1284,
        "netLongsLow": 0,
        "netShortsOpen": null,
        "netShortsClose": -3066,
        "netShortsHigh": 0,
        "netShortsLow": -3066
    },
    {
        "id": null,
        "exchangeName": null,
        "symbol": null,
        "baseCoin": null,
        "begin": 1734408000000,
        "interval": "15m",
        "netLongsOpen": null,
        "netLongsHigh": 149,
        "netLongsClose": -4190,
        "netLongsLow": -4190,
        "netShortsOpen": null,
        "netShortsClose": -1517,
        "netShortsHigh": 38,
        "netShortsLow": -1517
    },
    {
        "id": null,
        "exchangeName": null,
        "symbol": null,
        "baseCoin": null,
        "begin": 1734408900000,
        "interval": "15m",
        "netLongsOpen": null,
        "netLongsHigh": 0,
        "netLongsClose": -4158,
        "netLongsLow": -4158,
        "netShortsOpen": null,
        "netShortsClose": 871,
        "netShortsHigh": 914,
        "netShortsLow": -60
    },
    {
        "id": null,
        "exchangeName": null,
        "symbol": null,
        "baseCoin": null,
        "begin": 1734409800000,
        "interval": "15m",
        "netLongsOpen": null,
        "netLongsHigh": 0,
        "netLongsClose": -5473,
        "netLongsLow": -5847,
        "netShortsOpen": null,
        "netShortsClose": 4728,
        "netShortsHigh": 5972,
        "netShortsLow": 0
    },
    {
        "id": null,
        "exchangeName": null,
        "symbol": null,
        "baseCoin": null,
        "begin": 1734410700000,
        "interval": "15m",
        "netLongsOpen": null,
        "netLongsHigh": 2195,
        "netLongsClose": 2195,
        "netLongsLow": -280,
        "netShortsOpen": null,
        "netShortsClose": -1633,
        "netShortsHigh": 441,
        "netShortsLow": -2570
    },
    {
        "id": null,
        "exchangeName": null,
        "symbol": null,
        "baseCoin": null,
        "begin": 1734411600000,
        "interval": "15m",
        "netLongsOpen": null,
        "netLongsHigh": 3552,
        "netLongsClose": 3136,
        "netLongsLow": 0,
        "netShortsOpen": null,
        "netShortsClose": -1352,
        "netShortsHigh": 0,
        "netShortsLow": -1686
    },
    {
        "id": null,
        "exchangeName": null,
        "symbol": null,
        "baseCoin": null,
        "begin": 1734412500000,
        "interval": "15m",
        "netLongsOpen": null,
        "netLongsHigh": 1328,
        "netLongsClose": 1328,
        "netLongsLow": 0,
        "netShortsOpen": null,
        "netShortsClose": 115,
        "netShortsHigh": 576,
        "netShortsLow": -458
    },
    {
        "id": null,
        "exchangeName": null,
        "symbol": null,
        "baseCoin": null,
        "begin": 1734413400000,
        "interval": "15m",
        "netLongsOpen": null,
        "netLongsHigh": 4070,
        "netLongsClose": 4070,
        "netLongsLow": 0,
        "netShortsOpen": null,
        "netShortsClose": 928,
        "netShortsHigh": 1069,
        "netShortsLow": -1725
    },
    {
        "id": null,
        "exchangeName": null,
        "symbol": null,
        "baseCoin": null,
        "begin": 1734414300000,
        "interval": "15m",
        "netLongsOpen": null,
        "netLongsHigh": 605,
        "netLongsClose": 184,
        "netLongsLow": -670,
        "netShortsOpen": null,
        "netShortsClose": 1440,
        "netShortsHigh": 2360,
        "netShortsLow": -486
    },
    {
        "id": null,
        "exchangeName": null,
        "symbol": null,
        "baseCoin": null,
        "begin": 1734415200000,
        "interval": "15m",
        "netLongsOpen": null,
        "netLongsHigh": 0,
        "netLongsClose": -318,
        "netLongsLow": -579,
        "netShortsOpen": null,
        "netShortsClose": 1561,
        "netShortsHigh": 1561,
        "netShortsLow": 0
    },
    {
        "id": null,
        "exchangeName": null,
        "symbol": null,
        "baseCoin": null,
        "begin": 1734416100000,
        "interval": "15m",
        "netLongsOpen": null,
        "netLongsHigh": 589,
        "netLongsClose": -3231,
        "netLongsLow": -3231,
        "netShortsOpen": null,
        "netShortsClose": 697,
        "netShortsHigh": 697,
        "netShortsLow": -2252
    },
    {
        "id": null,
        "exchangeName": null,
        "symbol": null,
        "baseCoin": null,
        "begin": 1734417000000,
        "interval": "15m",
        "netLongsOpen": null,
        "netLongsHigh": 6145,
        "netLongsClose": 6145,
        "netLongsLow": -420,
        "netShortsOpen": null,
        "netShortsClose": -4043,
        "netShortsHigh": 0,
        "netShortsLow": -4043
    },
    {
        "id": null,
        "exchangeName": null,
        "symbol": null,
        "baseCoin": null,
        "begin": 1734417900000,
        "interval": "15m",
        "netLongsOpen": null,
        "netLongsHigh": 258,
        "netLongsClose": -1994,
        "netLongsLow": -3423,
        "netShortsOpen": null,
        "netShortsClose": -966,
        "netShortsHigh": 947,
        "netShortsLow": -966
    },
    {
        "id": null,
        "exchangeName": null,
        "symbol": null,
        "baseCoin": null,
        "begin": 1734418800000,
        "interval": "15m",
        "netLongsOpen": null,
        "netLongsHigh": 1712,
        "netLongsClose": 682,
        "netLongsLow": -178,
        "netShortsOpen": null,
        "netShortsClose": -2453,
        "netShortsHigh": 414,
        "netShortsLow": -2453
    },
    {
        "id": null,
        "exchangeName": null,
        "symbol": null,
        "baseCoin": null,
        "begin": 1734419700000,
        "interval": "15m",
        "netLongsOpen": null,
        "netLongsHigh": 3808,
        "netLongsClose": 3808,
        "netLongsLow": -1871,
        "netShortsOpen": null,
        "netShortsClose": -2894,
        "netShortsHigh": 0,
        "netShortsLow": -2894
    },
    {
        "id": null,
        "exchangeName": null,
        "symbol": null,
        "baseCoin": null,
        "begin": 1734420600000,
        "interval": "15m",
        "netLongsOpen": null,
        "netLongsHigh": 611,
        "netLongsClose": -389,
        "netLongsLow": -7355,
        "netShortsOpen": null,
        "netShortsClose": 16454,
        "netShortsHigh": 17309,
        "netShortsLow": -370
    },
    {
        "id": null,
        "exchangeName": null,
        "symbol": null,
        "baseCoin": null,
        "begin": 1734421500000,
        "interval": "15m",
        "netLongsOpen": null,
        "netLongsHigh": 19,
        "netLongsClose": -2448,
        "netLongsLow": -3485,
        "netShortsOpen": null,
        "netShortsClose": 1191,
        "netShortsHigh": 1554,
        "netShortsLow": -304
    },
    {
        "id": null,
        "exchangeName": null,
        "symbol": null,
        "baseCoin": null,
        "begin": 1734422400000,
        "interval": "15m",
        "netLongsOpen": null,
        "netLongsHigh": 2804,
        "netLongsClose": 2804,
        "netLongsLow": 0,
        "netShortsOpen": null,
        "netShortsClose": -1395,
        "netShortsHigh": 0,
        "netShortsLow": -1395
    },
    {
        "id": null,
        "exchangeName": null,
        "symbol": null,
        "baseCoin": null,
        "begin": 1734423300000,
        "interval": "15m",
        "netLongsOpen": null,
        "netLongsHigh": 4727,
        "netLongsClose": 4727,
        "netLongsLow": -747,
        "netShortsOpen": null,
        "netShortsClose": -1308,
        "netShortsHigh": 1065,
        "netShortsLow": -1308
    },
    {
        "id": null,
        "exchangeName": null,
        "symbol": null,
        "baseCoin": null,
        "begin": 1734424200000,
        "interval": "15m",
        "netLongsOpen": null,
        "netLongsHigh": 1578,
        "netLongsClose": 1578,
        "netLongsLow": -2153,
        "netShortsOpen": null,
        "netShortsClose": -508,
        "netShortsHigh": 1161,
        "netShortsLow": -508
    },
    {
        "id": null,
        "exchangeName": null,
        "symbol": null,
        "baseCoin": null,
        "begin": 1734425100000,
        "interval": "15m",
        "netLongsOpen": null,
        "netLongsHigh": 0,
        "netLongsClose": -9646,
        "netLongsLow": -9646,
        "netShortsOpen": null,
        "netShortsClose": 5930,
        "netShortsHigh": 5930,
        "netShortsLow": 0
    },
    {
        "id": null,
        "exchangeName": null,
        "symbol": null,
        "baseCoin": null,
        "begin": 1734426000000,
        "interval": "15m",
        "netLongsOpen": null,
        "netLongsHigh": 3184,
        "netLongsClose": 1695,
        "netLongsLow": 0,
        "netShortsOpen": null,
        "netShortsClose": 3254,
        "netShortsHigh": 3389,
        "netShortsLow": 0
    },
    {
        "id": null,
        "exchangeName": null,
        "symbol": null,
        "baseCoin": null,
        "begin": 1734426900000,
        "interval": "15m",
        "netLongsOpen": null,
        "netLongsHigh": 2406,
        "netLongsClose": 2406,
        "netLongsLow": 0,
        "netShortsOpen": null,
        "netShortsClose": 115,
        "netShortsHigh": 555,
        "netShortsLow": -1118
    },
    {
        "id": null,
        "exchangeName": null,
        "symbol": null,
        "baseCoin": null,
        "begin": 1734427800000,
        "interval": "15m",
        "netLongsOpen": null,
        "netLongsHigh": 5147,
        "netLongsClose": 5147,
        "netLongsLow": 0,
        "netShortsOpen": null,
        "netShortsClose": -7666,
        "netShortsHigh": 0,
        "netShortsLow": -7666
    },
    {
        "id": null,
        "exchangeName": null,
        "symbol": null,
        "baseCoin": null,
        "begin": 1734428700000,
        "interval": "15m",
        "netLongsOpen": null,
        "netLongsHigh": 7756,
        "netLongsClose": 5768,
        "netLongsLow": 0,
        "netShortsOpen": null,
        "netShortsClose": -11272,
        "netShortsHigh": 0,
        "netShortsLow": -11436
    },
    {
        "id": null,
        "exchangeName": null,
        "symbol": null,
        "baseCoin": null,
        "begin": 1734429600000,
        "interval": "15m",
        "netLongsOpen": null,
        "netLongsHigh": 0,
        "netLongsClose": -1691,
        "netLongsLow": -3591,
        "netShortsOpen": null,
        "netShortsClose": -854,
        "netShortsHigh": 2265,
        "netShortsLow": -854
    },
    {
        "id": null,
        "exchangeName": null,
        "symbol": null,
        "baseCoin": null,
        "begin": 1734430500000,
        "interval": "15m",
        "netLongsOpen": null,
        "netLongsHigh": 0,
        "netLongsClose": -6195,
        "netLongsLow": -6440,
        "netShortsOpen": null,
        "netShortsClose": 5610,
        "netShortsHigh": 5610,
        "netShortsLow": 0
    },
    {
        "id": null,
        "exchangeName": null,
        "symbol": null,
        "baseCoin": null,
        "begin": 1734431400000,
        "interval": "15m",
        "netLongsOpen": null,
        "netLongsHigh": 0,
        "netLongsClose": -3353,
        "netLongsLow": -4515,
        "netShortsOpen": null,
        "netShortsClose": -177,
        "netShortsHigh": 1851,
        "netShortsLow": -177
    },
    {
        "id": null,
        "exchangeName": null,
        "symbol": null,
        "baseCoin": null,
        "begin": 1734432300000,
        "interval": "15m",
        "netLongsOpen": null,
        "netLongsHigh": 3640,
        "netLongsClose": 3153,
        "netLongsLow": 0,
        "netShortsOpen": null,
        "netShortsClose": -4629,
        "netShortsHigh": 0,
        "netShortsLow": -4629
    },
    {
        "id": null,
        "exchangeName": null,
        "symbol": null,
        "baseCoin": null,
        "begin": 1734433200000,
        "interval": "15m",
        "netLongsOpen": null,
        "netLongsHigh": 3530,
        "netLongsClose": 3530,
        "netLongsLow": -907,
        "netShortsOpen": null,
        "netShortsClose": -1330,
        "netShortsHigh": 2159,
        "netShortsLow": -1330
    },
    {
        "id": null,
        "exchangeName": null,
        "symbol": null,
        "baseCoin": null,
        "begin": 1734434100000,
        "interval": "15m",
        "netLongsOpen": null,
        "netLongsHigh": 3433,
        "netLongsClose": -1820,
        "netLongsLow": -1820,
        "netShortsOpen": null,
        "netShortsClose": 789,
        "netShortsHigh": 999,
        "netShortsLow": -1438
    },
    {
        "id": null,
        "exchangeName": null,
        "symbol": null,
        "baseCoin": null,
        "begin": 1734435000000,
        "interval": "15m",
        "netLongsOpen": null,
        "netLongsHigh": 3627,
        "netLongsClose": 2871,
        "netLongsLow": 0,
        "netShortsOpen": null,
        "netShortsClose": -2883,
        "netShortsHigh": 0,
        "netShortsLow": -2883
    },
    {
        "id": null,
        "exchangeName": null,
        "symbol": null,
        "baseCoin": null,
        "begin": 1734435900000,
        "interval": "15m",
        "netLongsOpen": null,
        "netLongsHigh": 0,
        "netLongsClose": -10217,
        "netLongsLow": -10217,
        "netShortsOpen": null,
        "netShortsClose": 7152,
        "netShortsHigh": 7152,
        "netShortsLow": 0
    },
    {
        "id": null,
        "exchangeName": null,
        "symbol": null,
        "baseCoin": null,
        "begin": 1734436800000,
        "interval": "15m",
        "netLongsOpen": null,
        "netLongsHigh": 1276,
        "netLongsClose": -1224,
        "netLongsLow": -1224,
        "netShortsOpen": null,
        "netShortsClose": 905,
        "netShortsHigh": 905,
        "netShortsLow": -1872
    },
    {
        "id": null,
        "exchangeName": null,
        "symbol": null,
        "baseCoin": null,
        "begin": 1734437700000,
        "interval": "15m",
        "netLongsOpen": null,
        "netLongsHigh": 4564,
        "netLongsClose": 4564,
        "netLongsLow": -375,
        "netShortsOpen": null,
        "netShortsClose": -1343,
        "netShortsHigh": 548,
        "netShortsLow": -1343
    },
    {
        "id": null,
        "exchangeName": null,
        "symbol": null,
        "baseCoin": null,
        "begin": 1734438600000,
        "interval": "15m",
        "netLongsOpen": null,
        "netLongsHigh": 6873,
        "netLongsClose": 4682,
        "netLongsLow": 0,
        "netShortsOpen": null,
        "netShortsClose": -6248,
        "netShortsHigh": 0,
        "netShortsLow": -6248
    },
    {
        "id": null,
        "exchangeName": null,
        "symbol": null,
        "baseCoin": null,
        "begin": 1734439500000,
        "interval": "15m",
        "netLongsOpen": null,
        "netLongsHigh": 580,
        "netLongsClose": -251,
        "netLongsLow": -654,
        "netShortsOpen": null,
        "netShortsClose": 1879,
        "netShortsHigh": 1879,
        "netShortsLow": -413
    },
    {
        "id": null,
        "exchangeName": null,
        "symbol": null,
        "baseCoin": null,
        "begin": 1734440400000,
        "interval": "15m",
        "netLongsOpen": null,
        "netLongsHigh": 0,
        "netLongsClose": -3608,
        "netLongsLow": -3608,
        "netShortsOpen": null,
        "netShortsClose": 214,
        "netShortsHigh": 1559,
        "netShortsLow": 0
    },
    {
        "id": null,
        "exchangeName": null,
        "symbol": null,
        "baseCoin": null,
        "begin": 1734441300000,
        "interval": "15m",
        "netLongsOpen": null,
        "netLongsHigh": 3025,
        "netLongsClose": 2570,
        "netLongsLow": -825,
        "netShortsOpen": null,
        "netShortsClose": 1665,
        "netShortsHigh": 1665,
        "netShortsLow": -1693
    },
    {
        "id": null,
        "exchangeName": null,
        "symbol": null,
        "baseCoin": null,
        "begin": 1734442200000,
        "interval": "15m",
        "netLongsOpen": null,
        "netLongsHigh": 4171,
        "netLongsClose": 4171,
        "netLongsLow": -794,
        "netShortsOpen": null,
        "netShortsClose": -2336,
        "netShortsHigh": 256,
        "netShortsLow": -2336
    },
    {
        "id": null,
        "exchangeName": null,
        "symbol": null,
        "baseCoin": null,
        "begin": 1734443100000,
        "interval": "15m",
        "netLongsOpen": null,
        "netLongsHigh": 1087,
        "netLongsClose": -3834,
        "netLongsLow": -3834,
        "netShortsOpen": null,
        "netShortsClose": 3398,
        "netShortsHigh": 3398,
        "netShortsLow": -782
    },
    {
        "id": null,
        "exchangeName": null,
        "symbol": null,
        "baseCoin": null,
        "begin": 1734444000000,
        "interval": "15m",
        "netLongsOpen": null,
        "netLongsHigh": 0,
        "netLongsClose": -2074,
        "netLongsLow": -5090,
        "netShortsOpen": null,
        "netShortsClose": 4694,
        "netShortsHigh": 5652,
        "netShortsLow": 0
    },
    {
        "id": null,
        "exchangeName": null,
        "symbol": null,
        "baseCoin": null,
        "begin": 1734444900000,
        "interval": "15m",
        "netLongsOpen": null,
        "netLongsHigh": 1,
        "netLongsClose": -1124,
        "netLongsLow": -1418,
        "netShortsOpen": null,
        "netShortsClose": 2448,
        "netShortsHigh": 2448,
        "netShortsLow": -348
    },
    {
        "id": null,
        "exchangeName": null,
        "symbol": null,
        "baseCoin": null,
        "begin": 1734445800000,
        "interval": "15m",
        "netLongsOpen": null,
        "netLongsHigh": 1552,
        "netLongsClose": -7431,
        "netLongsLow": -7431,
        "netShortsOpen": null,
        "netShortsClose": 4195,
        "netShortsHigh": 4195,
        "netShortsLow": -433
    },
    {
        "id": null,
        "exchangeName": null,
        "symbol": null,
        "baseCoin": null,
        "begin": 1734446700000,
        "interval": "15m",
        "netLongsOpen": null,
        "netLongsHigh": 5623,
        "netLongsClose": 5623,
        "netLongsLow": 0,
        "netShortsOpen": null,
        "netShortsClose": -795,
        "netShortsHigh": 482,
        "netShortsLow": -795
    },
    {
        "id": null,
        "exchangeName": null,
        "symbol": null,
        "baseCoin": null,
        "begin": 1734447600000,
        "interval": "15m",
        "netLongsOpen": null,
        "netLongsHigh": 0,
        "netLongsClose": -14314,
        "netLongsLow": -14314,
        "netShortsOpen": null,
        "netShortsClose": 13417,
        "netShortsHigh": 13417,
        "netShortsLow": 0
    },
    {
        "id": null,
        "exchangeName": null,
        "symbol": null,
        "baseCoin": null,
        "begin": 1734448500000,
        "interval": "15m",
        "netLongsOpen": null,
        "netLongsHigh": 0,
        "netLongsClose": -22718,
        "netLongsLow": -25888,
        "netShortsOpen": null,
        "netShortsClose": 13364,
        "netShortsHigh": 20964,
        "netShortsLow": -2265
    },
    {
        "id": null,
        "exchangeName": null,
        "symbol": null,
        "baseCoin": null,
        "begin": 1734449400000,
        "interval": "15m",
        "netLongsOpen": null,
        "netLongsHigh": 25643,
        "netLongsClose": 25643,
        "netLongsLow": 0,
        "netShortsOpen": null,
        "netShortsClose": -10377,
        "netShortsHigh": 0,
        "netShortsLow": -11269
    },
    {
        "id": null,
        "exchangeName": null,
        "symbol": null,
        "baseCoin": null,
        "begin": 1734450300000,
        "interval": "15m",
        "netLongsOpen": null,
        "netLongsHigh": 935,
        "netLongsClose": -1393,
        "netLongsLow": -5317,
        "netShortsOpen": null,
        "netShortsClose": 4753,
        "netShortsHigh": 5747,
        "netShortsLow": -372
    }
]